{
  "type": "FeatureCollection",
  "features": [
    {
      "type": "Feature",
      "properties": {
        "description": "Ponte da Barra - car BEHIND accident (same direction, will be notified)"
      },
      "geometry": {
        "coordinates": [
          [
            -8.679675562834035,
            40.606846088610210
          ],
          [
            -8.679805161832998,
            40.606882529430055
          ],
          [
            -8.679934760831960,
            40.606918970249900
          ],
          [
            -8.680064359830923,
            40.606955411069744
          ],
          [
            -8.680193958829886,
            40.606991851889589
          ],
          [
            -8.680323557828848,
            40.607028292709434
          ],
          [
            -8.680453156827811,
            40.607064733529279
          ],
          [
            -8.680582755826774,
            40.607101174349123
          ],
          [
            -8.680712354825736,
            40.607137615168968
          ],
          [
            -8.680841953824699,
            40.607174055988813
          ],
          [
            -8.680971552823662,
            40.607210496808658
          ],
          [
            -8.681101151822624,
            40.607246937628502
          ],
          [
            -8.681230750821587,
            40.607283378448347
          ],
          [
            -8.681360349820550,
            40.607319819268192
          ],
          [
            -8.681489948819512,
            40.607356260088037
          ],
          [
            -8.681619547818475,
            40.607392700907881
          ],
          [
            -8.681749146817438,
            40.607429141727726
          ],
          [
            -8.681878745816400,
            40.607465582547571
          ],
          [
            -8.682008344815363,
            40.607502023367416
          ],
          [
            -8.682137943814325,
            40.607538464187260
          ]
        ],
        "type": "LineString"
      }
    }
  ]
}
